{
    "DNDConfig": null,
    "__parentReadjusting__": false,
    "_height_": {
        "type": "string",
        "value": "92%"
    },
    "_left_": {
        "type": "string",
        "value": "0%"
    },
    "_margin_": [
        0,
        0,
        0,
        0
    ],
    "_orientation_": 6,
    "_padding_": [
        0,
        0,
        0,
        0
    ],
    "_percent_": true,
    "_skin_": "s4a31085b0d04fe3bc8fde811c681733",
    "_top_": {
        "type": "string",
        "value": "8%"
    },
    "_width_": {
        "type": "string",
        "value": "100%"
    },
    "allboxes": [],
    "autogrowmode": 0,
    "canUpdateUI": true,
    "children": [
        "segFeaturesList"
    ],
    "clipbounds": true,
    "containerweight": 100,
    "enablescrolling": true,
    "id": "flxBody",
    "info": null,
    "iscustomlayout": false,
    "isvisible": true,
    "kuid": "jdd7f20cd0b84ae1bb86d020ed4c2198",
    "layouttype": 2,
    "name": "kony.ui.FlexContainer",
    "parent": "frmLanding",
    "pf": "frmLanding",
    "retaincontentalignment": false,
    "retainflexpositionproperties": false,
    "snapgridsize": 10,
    "snaptogrid": true,
    "wType": "FlexContainer",
    "widgetalignment": 1,
    "zindex": 1
}